{
  "doclist": [
    {
      "site-ranking": "ssoar-d1758", 
      "docid": "ssoar-d1765"
    }, 
    {
      "site-ranking": "ssoar-d1774", 
      "docid": "ssoar-d1779"
    }, 
    {
      "site-ranking": "ssoar-d1773", 
      "docid": "ssoar-d1782"
    }, 
    {
      "site-ranking": "ssoar-d1772", 
      "docid": "ssoar-d1763"
    }, 
    {
      "site-ranking": "ssoar-d1770", 
      "docid": "ssoar-d1803"
    }, 
    {
      "site-ranking": "ssoar-d1771", 
      "docid": "ssoar-d1788"
    }, 
    {
      "site-ranking": "ssoar-d1755", 
      "docid": "ssoar-d316"
    }, 
    {
      "site-ranking": "ssoar-d1760", 
      "docid": "ssoar-d1750"
    }, 
    {
      "site-ranking": "ssoar-d1762", 
      "docid": "ssoar-d1775"
    }, 
    {
      "site-ranking": "ssoar-d1763", 
      "docid": "ssoar-d1761"
    }, 
    {
      "site-ranking": "ssoar-d1761", 
      "docid": "ssoar-d1797"
    }, 
    {
      "site-ranking": "ssoar-d1775", 
      "docid": "ssoar-d1772"
    }, 
    {
      "site-ranking": "ssoar-d1756", 
      "docid": "ssoar-d1745"
    }, 
    {
      "site-ranking": "ssoar-d1759", 
      "docid": "ssoar-d1767"
    }, 
    {
      "site-ranking": "ssoar-d1754", 
      "docid": "ssoar-d1804"
    }, 
    {
      "site-ranking": "ssoar-d1776", 
      "docid": "ssoar-d1802"
    }, 
    {
      "site-ranking": "ssoar-d1757", 
      "docid": "ssoar-d1754"
    }, 
    {
      "site-ranking": "ssoar-d1765", 
      "docid": "ssoar-d1771"
    }, 
    {
      "site-ranking": "ssoar-d1768", 
      "docid": "ssoar-d1756"
    }, 
    {
      "site-ranking": "ssoar-d1766", 
      "docid": "ssoar-d1773"
    }, 
    {
      "site-ranking": "ssoar-d1767", 
      "docid": "ssoar-d1740"
    }, 
    {
      "site-ranking": "ssoar-d1769", 
      "docid": "ssoar-d1735"
    }, 
    {
      "site-ranking": "ssoar-d1764", 
      "docid": "ssoar-d1809"
    }, 
    {
      "site-ranking": "ssoar-d1777", 
      "docid": "ssoar-d1786"
    }, 
    {
      "site-ranking": "ssoar-d1778", 
      "docid": "ssoar-d1792"
    }, 
    {
      "site-ranking": "ssoar-d1779", 
      "docid": "ssoar-d1752"
    }, 
    {
      "site-ranking": "ssoar-d1783", 
      "docid": "ssoar-d816"
    }, 
    {
      "site-ranking": "ssoar-d1781", 
      "docid": "ssoar-d1785"
    }, 
    {
      "site-ranking": "ssoar-d1782", 
      "docid": "ssoar-d1746"
    }, 
    {
      "site-ranking": "ssoar-d1780", 
      "docid": "ssoar-d1743"
    }, 
    {
      "site-ranking": "ssoar-d1784", 
      "docid": "ssoar-d822"
    }, 
    {
      "site-ranking": "ssoar-d1785", 
      "docid": "ssoar-d1808"
    }, 
    {
      "site-ranking": "ssoar-d1786", 
      "docid": "ssoar-d1796"
    }, 
    {
      "site-ranking": "ssoar-d1788", 
      "docid": "ssoar-d1764"
    }, 
    {
      "site-ranking": "ssoar-d1789", 
      "docid": "ssoar-d1760"
    }, 
    {
      "site-ranking": "ssoar-d1790", 
      "docid": "ssoar-d1755"
    }, 
    {
      "site-ranking": "ssoar-d1787", 
      "docid": "ssoar-d1810"
    }, 
    {
      "site-ranking": "ssoar-d1812", 
      "docid": "ssoar-d1781"
    }, 
    {
      "site-ranking": "ssoar-d1791", 
      "docid": "ssoar-d827"
    }, 
    {
      "site-ranking": "ssoar-d1793", 
      "docid": "ssoar-d1783"
    }, 
    {
      "site-ranking": "ssoar-d1792", 
      "docid": "ssoar-d1793"
    }, 
    {
      "site-ranking": "ssoar-d1811", 
      "docid": "ssoar-d1776"
    }, 
    {
      "site-ranking": "ssoar-d1794", 
      "docid": "ssoar-d1799"
    }, 
    {
      "site-ranking": "ssoar-d1795", 
      "docid": "ssoar-d1742"
    }, 
    {
      "site-ranking": "ssoar-d1720", 
      "docid": "ssoar-d1770"
    }, 
    {
      "site-ranking": "ssoar-d1796", 
      "docid": "ssoar-d1758"
    }, 
    {
      "site-ranking": "ssoar-d1805", 
      "docid": "ssoar-d1738"
    }, 
    {
      "site-ranking": "ssoar-d1803", 
      "docid": "ssoar-d1747"
    }, 
    {
      "site-ranking": "ssoar-d1804", 
      "docid": "ssoar-d1805"
    }, 
    {
      "site-ranking": "ssoar-d1806", 
      "docid": "ssoar-d1780"
    }, 
    {
      "site-ranking": "ssoar-d316", 
      "docid": "ssoar-d570"
    }, 
    {
      "site-ranking": "ssoar-d1752", 
      "docid": "ssoar-d1720"
    }, 
    {
      "site-ranking": "ssoar-d1745", 
      "docid": "ssoar-d1741"
    }, 
    {
      "site-ranking": "ssoar-d1749", 
      "docid": "ssoar-d1795"
    }, 
    {
      "site-ranking": "ssoar-d1751", 
      "docid": "ssoar-d1768"
    }, 
    {
      "site-ranking": "ssoar-d1750", 
      "docid": "ssoar-d1757"
    }, 
    {
      "site-ranking": "ssoar-d1753", 
      "docid": "ssoar-d1777"
    }, 
    {
      "site-ranking": "ssoar-d1739", 
      "docid": "ssoar-d1787"
    }, 
    {
      "site-ranking": "ssoar-d1735", 
      "docid": "ssoar-d1774"
    }, 
    {
      "site-ranking": "ssoar-d1736", 
      "docid": "ssoar-d1739"
    }, 
    {
      "site-ranking": "ssoar-d1737", 
      "docid": "ssoar-d1789"
    }, 
    {
      "site-ranking": "ssoar-d1738", 
      "docid": "ssoar-d1791"
    }, 
    {
      "site-ranking": "ssoar-d1740", 
      "docid": "ssoar-d1751"
    }, 
    {
      "site-ranking": "ssoar-d1741", 
      "docid": "ssoar-d1762"
    }, 
    {
      "site-ranking": "ssoar-d570", 
      "docid": "ssoar-d821"
    }, 
    {
      "site-ranking": "ssoar-d827", 
      "docid": "ssoar-d1736"
    }, 
    {
      "site-ranking": "ssoar-d1748", 
      "docid": "ssoar-d1790"
    }, 
    {
      "site-ranking": "ssoar-d1747", 
      "docid": "ssoar-d1794"
    }, 
    {
      "site-ranking": "ssoar-d1746", 
      "docid": "ssoar-d1801"
    }, 
    {
      "site-ranking": "ssoar-d1744", 
      "docid": "ssoar-d1766"
    }, 
    {
      "site-ranking": "ssoar-d816", 
      "docid": "ssoar-d1744"
    }, 
    {
      "site-ranking": "ssoar-d1742", 
      "docid": "ssoar-d1807"
    }, 
    {
      "site-ranking": "ssoar-d1743", 
      "docid": "ssoar-d1769"
    }, 
    {
      "site-ranking": "ssoar-d822", 
      "docid": "ssoar-d1737"
    }, 
    {
      "site-ranking": "ssoar-d821", 
      "docid": "ssoar-d1798"
    }, 
    {
      "site-ranking": "ssoar-d1798", 
      "docid": "ssoar-d1759"
    }, 
    {
      "site-ranking": "ssoar-d1799", 
      "docid": "ssoar-d1753"
    }, 
    {
      "site-ranking": "ssoar-d1801", 
      "docid": "ssoar-d1778"
    }, 
    {
      "site-ranking": "ssoar-d1802", 
      "docid": "ssoar-d1749"
    }, 
    {
      "site-ranking": "ssoar-d1797", 
      "docid": "ssoar-d1806"
    }, 
    {
      "site-ranking": "ssoar-d1800", 
      "docid": "ssoar-d1800"
    }, 
    {
      "site-ranking": "ssoar-d1807", 
      "docid": "ssoar-d1812"
    }, 
    {
      "site-ranking": "ssoar-d1810", 
      "docid": "ssoar-d1748"
    }, 
    {
      "site-ranking": "ssoar-d1808", 
      "docid": "ssoar-d1784"
    }, 
    {
      "site-ranking": "ssoar-d1809", 
      "docid": "ssoar-d1811"
    }
  ], 
  "runid": "css-solr", 
  "qid": "ssoar-q23"
}