{
  "doclist": [
    {
      "site-ranking": "ssoar-d10810", 
      "docid": "ssoar-d10806"
    }, 
    {
      "site-ranking": "ssoar-d5082", 
      "docid": "ssoar-d7164"
    }, 
    {
      "site-ranking": "ssoar-d11940", 
      "docid": "ssoar-d5082"
    }, 
    {
      "site-ranking": "ssoar-d7164", 
      "docid": "ssoar-d10324"
    }, 
    {
      "site-ranking": "ssoar-d10806", 
      "docid": "ssoar-d7163"
    }, 
    {
      "site-ranking": "ssoar-d7163", 
      "docid": "ssoar-d11940"
    }, 
    {
      "site-ranking": "ssoar-d10324", 
      "docid": "ssoar-d10810"
    }, 
    {
      "site-ranking": "ssoar-d11941", 
      "docid": "ssoar-d11955"
    }, 
    {
      "site-ranking": "ssoar-d10780", 
      "docid": "ssoar-d11941"
    }, 
    {
      "site-ranking": "ssoar-d11942", 
      "docid": "ssoar-d11958"
    }, 
    {
      "site-ranking": "ssoar-d1974", 
      "docid": "ssoar-d11942"
    }, 
    {
      "site-ranking": "ssoar-d11943", 
      "docid": "ssoar-d7166"
    }, 
    {
      "site-ranking": "ssoar-d7152", 
      "docid": "ssoar-d11952"
    }, 
    {
      "site-ranking": "ssoar-d8549", 
      "docid": "ssoar-d4808"
    }, 
    {
      "site-ranking": "ssoar-d10331", 
      "docid": "ssoar-d11953"
    }, 
    {
      "site-ranking": "ssoar-d11944", 
      "docid": "ssoar-d10809"
    }, 
    {
      "site-ranking": "ssoar-d10327", 
      "docid": "ssoar-d7167"
    }, 
    {
      "site-ranking": "ssoar-d11945", 
      "docid": "ssoar-d11950"
    }, 
    {
      "site-ranking": "ssoar-d11946", 
      "docid": "ssoar-d11957"
    }, 
    {
      "site-ranking": "ssoar-d4795", 
      "docid": "ssoar-d11948"
    }, 
    {
      "site-ranking": "ssoar-d11947", 
      "docid": "ssoar-d11944"
    }, 
    {
      "site-ranking": "ssoar-d11948", 
      "docid": "ssoar-d10326"
    }, 
    {
      "site-ranking": "ssoar-d4796", 
      "docid": "ssoar-d11960"
    }, 
    {
      "site-ranking": "ssoar-d11949", 
      "docid": "ssoar-d11949"
    }, 
    {
      "site-ranking": "ssoar-d7116", 
      "docid": "ssoar-d11956"
    }, 
    {
      "site-ranking": "ssoar-d11950", 
      "docid": "ssoar-d11963"
    }, 
    {
      "site-ranking": "ssoar-d11951", 
      "docid": "ssoar-d11962"
    }, 
    {
      "site-ranking": "ssoar-d11952", 
      "docid": "ssoar-d11945"
    }, 
    {
      "site-ranking": "ssoar-d11953", 
      "docid": "ssoar-d7165"
    }, 
    {
      "site-ranking": "ssoar-d10326", 
      "docid": "ssoar-d10795"
    }, 
    {
      "site-ranking": "ssoar-d10809", 
      "docid": "ssoar-d11947"
    }, 
    {
      "site-ranking": "ssoar-d11954", 
      "docid": "ssoar-d7116"
    }, 
    {
      "site-ranking": "ssoar-d7169", 
      "docid": "ssoar-d4830"
    }, 
    {
      "site-ranking": "ssoar-d11955", 
      "docid": "ssoar-d8549"
    }, 
    {
      "site-ranking": "ssoar-d11956", 
      "docid": "ssoar-d10804"
    }, 
    {
      "site-ranking": "ssoar-d7115", 
      "docid": "ssoar-d10819"
    }, 
    {
      "site-ranking": "ssoar-d11957", 
      "docid": "ssoar-d10331"
    }, 
    {
      "site-ranking": "ssoar-d10795", 
      "docid": "ssoar-d10325"
    }, 
    {
      "site-ranking": "ssoar-d11958", 
      "docid": "ssoar-d11946"
    }, 
    {
      "site-ranking": "ssoar-d7166", 
      "docid": "ssoar-d10329"
    }, 
    {
      "site-ranking": "ssoar-d7162", 
      "docid": "ssoar-d7169"
    }, 
    {
      "site-ranking": "ssoar-d11959", 
      "docid": "ssoar-d7115"
    }, 
    {
      "site-ranking": "ssoar-d10323", 
      "docid": "ssoar-d11954"
    }, 
    {
      "site-ranking": "ssoar-d4830", 
      "docid": "ssoar-d10322"
    }, 
    {
      "site-ranking": "ssoar-d11960", 
      "docid": "ssoar-d11951"
    }, 
    {
      "site-ranking": "ssoar-d10804", 
      "docid": "ssoar-d7161"
    }, 
    {
      "site-ranking": "ssoar-d7167", 
      "docid": "ssoar-d10327"
    }, 
    {
      "site-ranking": "ssoar-d10329", 
      "docid": "ssoar-d11943"
    }, 
    {
      "site-ranking": "ssoar-d4808", 
      "docid": "ssoar-d7158"
    }, 
    {
      "site-ranking": "ssoar-d7165", 
      "docid": "ssoar-d7162"
    }, 
    {
      "site-ranking": "ssoar-d7161", 
      "docid": "ssoar-d7152"
    }, 
    {
      "site-ranking": "ssoar-d11961", 
      "docid": "ssoar-d10323"
    }, 
    {
      "site-ranking": "ssoar-d10819", 
      "docid": "ssoar-d11959"
    }, 
    {
      "site-ranking": "ssoar-d10325", 
      "docid": "ssoar-d1974"
    }, 
    {
      "site-ranking": "ssoar-d11962", 
      "docid": "ssoar-d10780"
    }, 
    {
      "site-ranking": "ssoar-d10322", 
      "docid": "ssoar-d11964"
    }, 
    {
      "site-ranking": "ssoar-d11963", 
      "docid": "ssoar-d4796"
    }, 
    {
      "site-ranking": "ssoar-d11964", 
      "docid": "ssoar-d4795"
    }, 
    {
      "site-ranking": "ssoar-d7158", 
      "docid": "ssoar-d11961"
    }
  ], 
  "runid": "css-solr", 
  "qid": "ssoar-q54"
}