{
  "doclist": [
    {
      "site-ranking": "ssoar-d4060", 
      "docid": "ssoar-d2823"
    }, 
    {
      "site-ranking": "ssoar-d4055", 
      "docid": "ssoar-d4390"
    }, 
    {
      "site-ranking": "ssoar-d7515", 
      "docid": "ssoar-d4384"
    }, 
    {
      "site-ranking": "ssoar-d7185", 
      "docid": "ssoar-d4385"
    }, 
    {
      "site-ranking": "ssoar-d7516", 
      "docid": "ssoar-d4443"
    }, 
    {
      "site-ranking": "ssoar-d7517", 
      "docid": "ssoar-d4386"
    }, 
    {
      "site-ranking": "ssoar-d7518", 
      "docid": "ssoar-d4448"
    }, 
    {
      "site-ranking": "ssoar-d3990", 
      "docid": "ssoar-d416"
    }, 
    {
      "site-ranking": "ssoar-d7519", 
      "docid": "ssoar-d2832"
    }, 
    {
      "site-ranking": "ssoar-d4981", 
      "docid": "ssoar-d7557"
    }, 
    {
      "site-ranking": "ssoar-d7520", 
      "docid": "ssoar-d415"
    }, 
    {
      "site-ranking": "ssoar-d4038", 
      "docid": "ssoar-d2831"
    }, 
    {
      "site-ranking": "ssoar-d4064", 
      "docid": "ssoar-d7516"
    }, 
    {
      "site-ranking": "ssoar-d4065", 
      "docid": "ssoar-d7257"
    }, 
    {
      "site-ranking": "ssoar-d7521", 
      "docid": "ssoar-d2371"
    }, 
    {
      "site-ranking": "ssoar-d7522", 
      "docid": "ssoar-d2374"
    }, 
    {
      "site-ranking": "ssoar-d7523", 
      "docid": "ssoar-d7259"
    }, 
    {
      "site-ranking": "ssoar-d7524", 
      "docid": "ssoar-d4054"
    }, 
    {
      "site-ranking": "ssoar-d7525", 
      "docid": "ssoar-d2373"
    }, 
    {
      "site-ranking": "ssoar-d7526", 
      "docid": "ssoar-d7558"
    }, 
    {
      "site-ranking": "ssoar-d4054", 
      "docid": "ssoar-d7544"
    }, 
    {
      "site-ranking": "ssoar-d370", 
      "docid": "ssoar-d370"
    }, 
    {
      "site-ranking": "ssoar-d7527", 
      "docid": "ssoar-d4055"
    }, 
    {
      "site-ranking": "ssoar-d4510", 
      "docid": "ssoar-d2370"
    }, 
    {
      "site-ranking": "ssoar-d7528", 
      "docid": "ssoar-d7517"
    }, 
    {
      "site-ranking": "ssoar-d4310", 
      "docid": "ssoar-d7521"
    }, 
    {
      "site-ranking": "ssoar-d7529", 
      "docid": "ssoar-d7522"
    }, 
    {
      "site-ranking": "ssoar-d7530", 
      "docid": "ssoar-d7250"
    }, 
    {
      "site-ranking": "ssoar-d7531", 
      "docid": "ssoar-d7543"
    }, 
    {
      "site-ranking": "ssoar-d3167", 
      "docid": "ssoar-d2830"
    }, 
    {
      "site-ranking": "ssoar-d2871", 
      "docid": "ssoar-d2829"
    }, 
    {
      "site-ranking": "ssoar-d7532", 
      "docid": "ssoar-d4065"
    }, 
    {
      "site-ranking": "ssoar-d7533", 
      "docid": "ssoar-d7067"
    }, 
    {
      "site-ranking": "ssoar-d7206", 
      "docid": "ssoar-d7518"
    }, 
    {
      "site-ranking": "ssoar-d7534", 
      "docid": "ssoar-d7237"
    }, 
    {
      "site-ranking": "ssoar-d2831", 
      "docid": "ssoar-d3990"
    }, 
    {
      "site-ranking": "ssoar-d7535", 
      "docid": "ssoar-d7577"
    }, 
    {
      "site-ranking": "ssoar-d7232", 
      "docid": "ssoar-d412"
    }, 
    {
      "site-ranking": "ssoar-d7536", 
      "docid": "ssoar-d7562"
    }, 
    {
      "site-ranking": "ssoar-d7537", 
      "docid": "ssoar-d4038"
    }, 
    {
      "site-ranking": "ssoar-d7236", 
      "docid": "ssoar-d7529"
    }, 
    {
      "site-ranking": "ssoar-d7237", 
      "docid": "ssoar-d7532"
    }, 
    {
      "site-ranking": "ssoar-d7538", 
      "docid": "ssoar-d7550"
    }, 
    {
      "site-ranking": "ssoar-d7539", 
      "docid": "ssoar-d7561"
    }, 
    {
      "site-ranking": "ssoar-d7540", 
      "docid": "ssoar-d4060"
    }, 
    {
      "site-ranking": "ssoar-d7541", 
      "docid": "ssoar-d7524"
    }, 
    {
      "site-ranking": "ssoar-d7250", 
      "docid": "ssoar-d7534"
    }, 
    {
      "site-ranking": "ssoar-d2371", 
      "docid": "ssoar-d7563"
    }, 
    {
      "site-ranking": "ssoar-d2370", 
      "docid": "ssoar-d7232"
    }, 
    {
      "site-ranking": "ssoar-d2373", 
      "docid": "ssoar-d7536"
    }, 
    {
      "site-ranking": "ssoar-d7257", 
      "docid": "ssoar-d7552"
    }, 
    {
      "site-ranking": "ssoar-d7259", 
      "docid": "ssoar-d7551"
    }, 
    {
      "site-ranking": "ssoar-d7542", 
      "docid": "ssoar-d4981"
    }, 
    {
      "site-ranking": "ssoar-d7543", 
      "docid": "ssoar-d4064"
    }, 
    {
      "site-ranking": "ssoar-d7269", 
      "docid": "ssoar-d2827"
    }, 
    {
      "site-ranking": "ssoar-d7544", 
      "docid": "ssoar-d7555"
    }, 
    {
      "site-ranking": "ssoar-d4448", 
      "docid": "ssoar-d7565"
    }, 
    {
      "site-ranking": "ssoar-d7545", 
      "docid": "ssoar-d2828"
    }, 
    {
      "site-ranking": "ssoar-d7546", 
      "docid": "ssoar-d7546"
    }, 
    {
      "site-ranking": "ssoar-d7547", 
      "docid": "ssoar-d7236"
    }, 
    {
      "site-ranking": "ssoar-d7548", 
      "docid": "ssoar-d7560"
    }, 
    {
      "site-ranking": "ssoar-d7549", 
      "docid": "ssoar-d7542"
    }, 
    {
      "site-ranking": "ssoar-d7550", 
      "docid": "ssoar-d7564"
    }, 
    {
      "site-ranking": "ssoar-d7551", 
      "docid": "ssoar-d7523"
    }, 
    {
      "site-ranking": "ssoar-d1102", 
      "docid": "ssoar-d4310"
    }, 
    {
      "site-ranking": "ssoar-d2374", 
      "docid": "ssoar-d7554"
    }, 
    {
      "site-ranking": "ssoar-d7552", 
      "docid": "ssoar-d7185"
    }, 
    {
      "site-ranking": "ssoar-d416", 
      "docid": "ssoar-d7553"
    }, 
    {
      "site-ranking": "ssoar-d7553", 
      "docid": "ssoar-d7535"
    }, 
    {
      "site-ranking": "ssoar-d7554", 
      "docid": "ssoar-d3167"
    }, 
    {
      "site-ranking": "ssoar-d7280", 
      "docid": "ssoar-d2820"
    }, 
    {
      "site-ranking": "ssoar-d7555", 
      "docid": "ssoar-d7548"
    }, 
    {
      "site-ranking": "ssoar-d2832", 
      "docid": "ssoar-d7540"
    }, 
    {
      "site-ranking": "ssoar-d4390", 
      "docid": "ssoar-d4510"
    }, 
    {
      "site-ranking": "ssoar-d1104", 
      "docid": "ssoar-d7525"
    }, 
    {
      "site-ranking": "ssoar-d7556", 
      "docid": "ssoar-d7533"
    }, 
    {
      "site-ranking": "ssoar-d4443", 
      "docid": "ssoar-d1104"
    }, 
    {
      "site-ranking": "ssoar-d7557", 
      "docid": "ssoar-d7539"
    }, 
    {
      "site-ranking": "ssoar-d7558", 
      "docid": "ssoar-d7527"
    }, 
    {
      "site-ranking": "ssoar-d412", 
      "docid": "ssoar-d7545"
    }, 
    {
      "site-ranking": "ssoar-d2820", 
      "docid": "ssoar-d7538"
    }, 
    {
      "site-ranking": "ssoar-d7559", 
      "docid": "ssoar-d7559"
    }, 
    {
      "site-ranking": "ssoar-d1098", 
      "docid": "ssoar-d7206"
    }, 
    {
      "site-ranking": "ssoar-d7560", 
      "docid": "ssoar-d1098"
    }, 
    {
      "site-ranking": "ssoar-d4384", 
      "docid": "ssoar-d7269"
    }, 
    {
      "site-ranking": "ssoar-d2823", 
      "docid": "ssoar-d7531"
    }, 
    {
      "site-ranking": "ssoar-d4386", 
      "docid": "ssoar-d7530"
    }, 
    {
      "site-ranking": "ssoar-d4385", 
      "docid": "ssoar-d7520"
    }, 
    {
      "site-ranking": "ssoar-d2829", 
      "docid": "ssoar-d1102"
    }, 
    {
      "site-ranking": "ssoar-d2830", 
      "docid": "ssoar-d7547"
    }, 
    {
      "site-ranking": "ssoar-d415", 
      "docid": "ssoar-d7549"
    }, 
    {
      "site-ranking": "ssoar-d7561", 
      "docid": "ssoar-d7556"
    }, 
    {
      "site-ranking": "ssoar-d2828", 
      "docid": "ssoar-d7537"
    }, 
    {
      "site-ranking": "ssoar-d2827", 
      "docid": "ssoar-d7528"
    }, 
    {
      "site-ranking": "ssoar-d7562", 
      "docid": "ssoar-d2871"
    }, 
    {
      "site-ranking": "ssoar-d7067", 
      "docid": "ssoar-d7519"
    }, 
    {
      "site-ranking": "ssoar-d7563", 
      "docid": "ssoar-d7526"
    }, 
    {
      "site-ranking": "ssoar-d7564", 
      "docid": "ssoar-d7280"
    }, 
    {
      "site-ranking": "ssoar-d7565", 
      "docid": "ssoar-d7541"
    }, 
    {
      "site-ranking": "ssoar-d7577", 
      "docid": "ssoar-d7515"
    }
  ], 
  "runid": "css-solr", 
  "qid": "ssoar-q72"
}